dot_aas_part_2_httprest_asset_administration_shell_registry_service_specification_client/__init__.py
dot_aas_part_2_httprest_asset_administration_shell_registry_service_specification_client/api/__init__.py
dot_aas_part_2_httprest_asset_administration_shell_registry_service_specification_client/api/registry_and_discovery_interface/__init__.py
dot_aas_part_2_httprest_asset_administration_shell_registry_service_specification_client/api/registry_and_discovery_interface/delete_all_shell_descriptors.py
dot_aas_part_2_httprest_asset_administration_shell_registry_service_specification_client/api/registry_and_discovery_interface/delete_asset_administration_shell_descriptor_by_id.py
dot_aas_part_2_httprest_asset_administration_shell_registry_service_specification_client/api/registry_and_discovery_interface/delete_submodel_descriptor_by_id_through_superpath.py
dot_aas_part_2_httprest_asset_administration_shell_registry_service_specification_client/api/registry_and_discovery_interface/get_all_asset_administration_shell_descriptors.py
dot_aas_part_2_httprest_asset_administration_shell_registry_service_specification_client/api/registry_and_discovery_interface/get_all_submodel_descriptors_through_superpath.py
dot_aas_part_2_httprest_asset_administration_shell_registry_service_specification_client/api/registry_and_discovery_interface/get_asset_administration_shell_descriptor_by_id.py
dot_aas_part_2_httprest_asset_administration_shell_registry_service_specification_client/api/registry_and_discovery_interface/get_description.py
dot_aas_part_2_httprest_asset_administration_shell_registry_service_specification_client/api/registry_and_discovery_interface/get_submodel_descriptor_by_id_through_superpath.py
dot_aas_part_2_httprest_asset_administration_shell_registry_service_specification_client/api/registry_and_discovery_interface/post_asset_administration_shell_descriptor.py
dot_aas_part_2_httprest_asset_administration_shell_registry_service_specification_client-2.0.dist-info/METADATA
dot_aas_part_2_httprest_asset_administration_shell_registry_service_specification_client-2.0.dist-info/WHEEL
dot_aas_part_2_httprest_asset_administration_shell_registry_service_specification_client-2.0.dist-info/RECORD
