Metadata-Version: 2.1
Name: dot-aas-part-2-httprest-asset-administration-shell-registry-service-specification-client
Version: 2.0
Summary: A client library for accessing DotAAS Part 2 | HTTP/REST | Asset Administration Shell Registry Service Specification
Requires-Python: >=3.8,<4.0
Classifier: Programming Language :: Python :: 3
Classifier: Programming Language :: Python :: 3.8
Classifier: Programming Language :: Python :: 3.9
Classifier: Programming Language :: Python :: 3.10
Classifier: Programming Language :: Python :: 3.11
Requires-Dist: attrs (>=21.3.0)
Requires-Dist: httpx (>=0.20.0,<0.28.0)
Requires-Dist: python-dateutil (>=2.8.0,<3.0.0)
